Metadata-Version: 2.1
Name: SPapi
Version: 1.1.0
Summary: API for jakksoft.com
Home-page: UNKNOWN
Author: Kreal
Author-email: lazo12kirill@gmail.com
License: UNKNOWN
Platform: UNKNOWN
